aslabs/dependencies/airtable/__init__.py
aslabs/dependencies/airtable/airtable.py
aslabs/dependencies/airtable/config.py
aslabs/dependencies/airtable/resolver.py
aslabs_dependencies_airtable-0.0.2.dist-info/WHEEL
aslabs_dependencies_airtable-0.0.2.dist-info/METADATA
aslabs_dependencies_airtable-0.0.2.dist-info/RECORD
