Metadata-Version: 2.1
Name: aslabs-dependencies-airtable
Version: 0.0.2
Summary: 
Author: Titusz Ban
Author-email: tituszban@antisociallabs.io
Requires-Python: >=3.9,<4.0
Classifier: Programming Language :: Python :: 3
Classifier: Programming Language :: Python :: 3.9
Classifier: Programming Language :: Python :: 3.10
Classifier: Programming Language :: Python :: 3.11
Requires-Dist: aslabs-dependencies
Requires-Dist: requests (>=2.27.1,<3.0.0)
